lighthouse/__init__.py
lighthouse/report.py
lighthouse/runner.py
lighthouse_python_plus-1.2.0.dist-info/LICENSE
lighthouse_python_plus-1.2.0.dist-info/METADATA
lighthouse_python_plus-1.2.0.dist-info/WHEEL
lighthouse_python_plus-1.2.0.dist-info/top_level.txt
lighthouse_python_plus-1.2.0.dist-info/RECORD
