Metadata-Version: 2.1
Name: lighthouse-python-plus
Version: 1.2.0
Summary: Lighthouse runner is a Python package that wraps the Lighthouse tool for easy integration into Python projects.
Author: alireza sharifi
Author-email: sharifialireza276@gmail.com
Project-URL: Github, https://github.com/sh-alireza/lighthouse-python-plus
License-File: LICENSE
Requires-Dist: tqdm (>=4.30)
